MANIFEST.in
README
cirrus.conf
requirements.txt
setup.py
test-requirements.txt
src/dockerstache/__init__.py
src/dockerstache/__main__.py
src/dockerstache/context.py
src/dockerstache/dockerstache.py
src/dockerstache/dotfile.py
src/dockerstache/templates.py
src/dockerstache.egg-info/PKG-INFO
src/dockerstache.egg-info/SOURCES.txt
src/dockerstache.egg-info/dependency_links.txt
src/dockerstache.egg-info/entry_points.txt
src/dockerstache.egg-info/requires.txt
src/dockerstache.egg-info/top_level.txt