Metadata-Version: 1.1
Name: dockerstache
Version: 0.0.8
Summary: Dockerfile templating tool with mustache templates
Home-page: https://github.com/evansde77/dockerstache
Author: evansde77
Author-email: evansde77.github@gmail.com
License: UNKNOWN
Platform: UNKNOWN
Provides: dockerstache
